[
  {
    "id": 1,
    "ime": "Dom zdravlja Topola",
    "opis": "Болница у Тополи је радила до 02.07.1962. године, када је основан Дом здравља са стационаром ”Даринка Радовић”, у чији састав су ушле следеће установе: Општа Болница у Тополи, Дом народног здравља у Тополи и Центар за мајку и дете у Тополи.
             Стационар у саставу Дома здравља у Тополи престаје са радом 01.04.1971.године.
             Дана 28.09.2002.године Дом здравља мења назив у Дом здравља ”Свети Ђорђе” Топола    . .",
    "webadresa": "https://dztopola.rs/",
    "slika": "http://novinice.rs/wp-content/uploads/2020/04/DSCN0903-1.jpg",
    },
]
